ba137_hyperfine_hamiltonian_solver/__init__.py
ba137_hyperfine_hamiltonian_solver/ba137_hyperfine_hamiltonian_solver.py
ba137_hyperfine_hamiltonian_solver-0.1.3.dist-info/licenses/LICENSE
ba137_hyperfine_hamiltonian_solver-0.1.3.dist-info/METADATA
ba137_hyperfine_hamiltonian_solver-0.1.3.dist-info/WHEEL
ba137_hyperfine_hamiltonian_solver-0.1.3.dist-info/top_level.txt
ba137_hyperfine_hamiltonian_solver-0.1.3.dist-info/RECORD
