Metadata-Version: 2.4
Name: Ba137_hyperfine_hamiltonian_solver
Version: 0.1.3
Summary: Hyperfine Hamiltonians, transition frequencies, and strengths for 137Ba+
Author-email: Gaurav Ashish Tathed <gatathed@uwaterloo.ca>
License: MIT License
Project-URL: Homepage, https://github.com/GauravTathed/Ba137_hyperfine_hamiltonian_solver
Project-URL: Issues, https://github.com/GauravTathed/Ba137_hyperfine_hamiltonian_solver/issues
Requires-Python: >=3.9
License-File: LICENSE
Requires-Dist: numpy
Requires-Dist: pandas
Requires-Dist: scipy
Dynamic: license-file
